rest_tools/__init__.py
rest_tools/canvas.py
rest_tools/clickup.py
rest_tools/common.py
rest_tools/directus.py
rest_tools/eventbrite.py
rest_tools/fusionauth.py
rest_tools/livestorm.py
rest_tools/mailchimp.py
rest_tools/pipedrive.py
rest_tools/prestashop.py
rest_tools/wordpress.py
rest_tools-0.7.2.dist-info/LICENSE
rest_tools-0.7.2.dist-info/METADATA
rest_tools-0.7.2.dist-info/WHEEL
rest_tools-0.7.2.dist-info/top_level.txt
rest_tools-0.7.2.dist-info/RECORD
