Metadata-Version: 2.1
Name: rest-tools
Version: 0.7.2
Summary: A collection of utilities to speak with JSON REST APIs
Home-page: https://github.com/willywongi/py-rest-tools
Author: Francesco Pongiluppi
Author-email: pongi@pongi.it
Project-URL: Bug Tracker, https://github.com/willywongi/py-rest-tools/issues
Classifier: Programming Language :: Python :: 3
Classifier: License :: OSI Approved :: GNU General Public License (GPL)
Classifier: Operating System :: OS Independent
Requires-Python: >=3.6
License-File: LICENSE
